mobile_validate/__init__.py
mobile_validate/check_list.py
mobile_validate/validator.py
mobile_validate-1.3.3.dist-info/LICENSE
mobile_validate-1.3.3.dist-info/METADATA
mobile_validate-1.3.3.dist-info/WHEEL
mobile_validate-1.3.3.dist-info/entry_points.txt
mobile_validate-1.3.3.dist-info/top_level.txt
mobile_validate-1.3.3.dist-info/RECORD
