Metadata-Version: 2.1
Name: mobile_validate
Version: 1.3.3
Home-page: https://github.com/taqsblaze/mobile-validate
Author: Tanaka Chinengundu
Author-email: tanakah30@gmail.com
License: MIT
Classifier: Development Status :: 3 - Alpha
Classifier: Intended Audience :: Developers
Classifier: Topic :: Communications
Classifier: Topic :: Utilities
Classifier: License :: OSI Approved :: MIT License
Classifier: Programming Language :: Python :: 3
Requires-Python: >=3.8
License-File: LICENSE
Requires-Dist: pip
Requires-Dist: phonenumbers
